mipyp/__init__.py
mipyp/__main__.py
mipyp/helper.py
mipyp/mipyp.py
mipyp/mipypro.py
mipypro/__init__.py
mipypro/__main__.py
mipypro/helper.py
mipypro/mipypro.py
orthofisher/__init__.py
orthofisher/__main__.py
orthofisher/args_processing.py
orthofisher/helper.py
orthofisher/orthofisher.py
orthofisher/parser.py
orthofisher/version.py
orthofisher-1.1.1.dist-info/LICENSE.md
orthofisher-1.1.1.dist-info/METADATA
orthofisher-1.1.1.dist-info/WHEEL
orthofisher-1.1.1.dist-info/entry_points.txt
orthofisher-1.1.1.dist-info/top_level.txt
orthofisher-1.1.1.dist-info/RECORD
