Metadata-Version: 2.1
Name: orthofisher
Version: 1.1.1
Summary: orthofisher
Home-page: https://github.com/JLSteenwyk/orthofisher.git
Author: Jacob L. Steenwyk
Author-email: jlsteenwyk@gmail.com
Classifier: Operating System :: OS Independent
Classifier: Intended Audience :: Science/Research
Classifier: Programming Language :: Python
Classifier: Programming Language :: Python :: 3.9
Classifier: Programming Language :: Python :: 3.10
Classifier: Programming Language :: Python :: 3.11
Classifier: Topic :: Scientific/Engineering
License-File: LICENSE.md
Requires-Dist: biopython >=1.82
Requires-Dist: numpy >=1.24.0
Requires-Dist: tqdm >=4.66.1
Requires-Dist: cython
